delta/cli/__init__.py
delta/cli/_version.py
delta/cli/exception.py
delta/cli/login.py
delta/cli/metrics.py
delta/cli/utils.py
delta/cli/version.py
delta/cli/components/__init__.py
delta/cli/components/build.py
delta/cli/components/delete.py
delta/cli/components/get.py
delta/cli/components/init.py
delta/cli/components/list.py
delta/cli/components/publish.py
delta/cli/components/update.py
delta/cli/components/template/manifest.py
delta/cli/components/template/workflow.yml
delta/cli/drive/__init__.py
delta/cli/drive/check.py
delta/cli/drive/update.py
delta/cli/drive/artifact/__init__.py
delta/cli/drive/artifact/add.py
delta/cli/drive/artifact/delete.py
delta/cli/drive/artifact/download.py
delta/cli/drive/artifact/get.py
delta/cli/drive/artifact/list.py
delta/cli/drive/dependency/__init__.py
delta/cli/drive/dependency/add.py
delta/cli/drive/dependency/delete.py
delta/cli/drive/dependency/list.py
delta/cli/drive/resource/__init__.py
delta/cli/drive/resource/add.py
delta/cli/drive/resource/delete.py
delta/cli/drive/resource/download.py
delta/cli/drive/resource/get.py
delta/cli/drive/resource/list.py
delta/cli/drive/resource/sync.py
delta/cli/run/__init__.py
delta/cli/run/configuration.py
delta/cli/run/delete.py
delta/cli/run/download.py
delta/cli/run/get.py
delta/cli/run/list.py
delta/cli/run/local.py
delta/cli/run/resume.py
delta/cli/run/start.py
delta/cli/run/stop.py
delta/cli/run/monitor/__init__.py
delta/cli/run/monitor/logs.py
delta/cli/run/monitor/status.py
delta/cli/schedule/__init__.py
delta/cli/schedule/add.py
delta/cli/schedule/delete.py
delta/cli/schedule/get.py
delta/cli/schedule/list.py
delta/cli/schedule/pause.py
delta/cli/schedule/resume.py
delta/cli/schedule/utils.py
deltatwin_cli-1.8.1.dist-info/METADATA
deltatwin_cli-1.8.1.dist-info/WHEEL
deltatwin_cli-1.8.1.dist-info/entry_points.txt
deltatwin_cli-1.8.1.dist-info/top_level.txt
deltatwin_cli-1.8.1.dist-info/RECORD
