Metadata-Version: 2.4
Name: deltatwin-cli
Version: 1.8.1
Summary: DeltaTwin command line for managing Delta project
Classifier: License :: OSI Approved :: GNU Lesser General Public License v3 (LGPLv3)
Requires-Python: ~=3.11
Requires-Dist: click>=8.1.3
Requires-Dist: rich>=13.7.0
Requires-Dist: delta-core~=1.2.7
Requires-Dist: humanize==4.10.0
Requires-Dist: plotext==5.3.2
